{
  "_class": "text",
  "attributedString": {
    "_class": "attributedString",
    "attributes": [
      {
        "_class": "stringAttribute",
        "attributes": {
          "MSAttributedStringColorAttribute": {
            "_class": "color",
            "alpha": 1,
            "blue": 0.6079225540161133,
            "green": 0.6078033447265625,
            "red": 0.6078922152519226
          },
          "MSAttributedStringFontAttribute": {
            "_class": "fontDescriptor",
            "attributes": {
              "name": "Helvetica-Bold",
              "size": 24
            }
          },
          "paragraphStyle": {
            "_class": "paragraphStyle"
          },
          "textStyleVerticalAlignmentKey": 0
        },
        "length": 19,
        "location": 0
      }
    ],
    "string": "Performance Audits\n"
  },
  "automaticallyDrawOnUnderlyingPath": false,
  "booleanOperation": -1,
  "do_objectID": "1BEC31AB-95E7-45EC-8A78-B156DD4D225D",
  "dontSynchroniseWithSymbol": false,
  "exportOptions": {
    "_class": "exportOptions",
    "do_objectID": "A5785837-84E9-47CF-9004-715A741C04DE",
    "exportFormats": [
    ],
    "includedLayerIds": [
    ],
    "layerOptions": 0,
    "shouldTrim": false
  },
  "frame": {
    "_class": "rect",
    "constrainProportions": false,
    "do_objectID": "623563B3-4506-46A4-B5E3-9211AAA6B116",
    "height": 58,
    "width": 228,
    "x": 74,
    "y": 2496
  },
  "glyphBounds": "{{1, 5}, {226, 19}}",
  "isFixedToViewport": false,
  "isFlippedHorizontal": false,
  "isFlippedVertical": false,
  "isLocked": false,
  "isVisible": true,
  "layerListExpandedType": 0,
  "lineSpacingBehaviour": 2,
  "name": "Branding-title Copy 2",
  "nameIsFixed": true,
  "resizingConstraint": 47,
  "resizingType": 0,
  "rotation": 0,
  "shouldBreakMaskChain": false,
  "style": {
    "_class": "style",
    "do_objectID": "4281F7F5-E07E-44CE-9195-144C8024E03A",
    "endMarkerType": 0,
    "miterLimit": 10,
    "startMarkerType": 0,
    "textStyle": {
      "_class": "textStyle",
      "do_objectID": "4EDC87DC-099C-4B03-8E1D-7C455C07F7C4",
      "encodedAttributes": {
        "MSAttributedStringColorAttribute": {
          "_class": "color",
          "alpha": 1,
          "blue": 0.6079225540161133,
          "green": 0.6078033447265625,
          "red": 0.6078922152519226
        },
        "MSAttributedStringFontAttribute": {
          "_class": "fontDescriptor",
          "attributes": {
            "name": "Helvetica-Bold",
            "size": 24
          }
        },
        "paragraphStyle": {
          "_class": "paragraphStyle"
        },
        "textStyleVerticalAlignmentKey": 0
      },
      "verticalAlignment": 0
    },
    "windingRule": 1
  },
  "textBehaviour": 0,
  "userInfo": {
    "com.animaapp.stc-sketch-plugin": {
      "kModelPropertiesKey": {
        "isAutoWidth": 1
      }
    }
  }
}