{
  "_class": "shapeGroup",
  "booleanOperation": 0,
  "clippingMaskMode": 0,
  "do_objectID": "3EE456F2-79A4-4F74-A516-24CEA98606E6",
  "exportOptions": {
    "_class": "exportOptions",
    "do_objectID": "C65D6FB9-1382-4DD0-89DC-178E55E1D658",
    "exportFormats": [
    ],
    "includedLayerIds": [
    ],
    "layerOptions": 0,
    "shouldTrim": false
  },
  "frame": {
    "_class": "rect",
    "constrainProportions": true,
    "do_objectID": "CA6F3C7F-A7AE-4F37-A871-FD2E143B191D",
    "height": 22.99999999999997,
    "width": 24.00000000000002,
    "x": 0,
    "y": 0
  },
  "hasClickThrough": false,
  "hasClippingMask": false,
  "isFixedToViewport": false,
  "isFlippedHorizontal": false,
  "isFlippedVertical": false,
  "isLocked": false,
  "isVisible": true,
  "layerListExpandedType": 1,
  "layers": [
    {
      "class": "oval",
      "id": "A519E1E8-0918-4538-A5F3-56713B99B1EC"
    }
  ],
  "name": "Oval",
  "nameIsFixed": true,
  "resizingConstraint": 63,
  "resizingType": 0,
  "rotation": 0,
  "shouldBreakMaskChain": false,
  "style": {
    "_class": "style",
    "borders": [
      {
        "_class": "border",
        "color": {
          "_class": "color",
          "alpha": 1,
          "blue": 0,
          "green": 0,
          "red": 0
        },
        "fillType": 0,
        "isEnabled": true,
        "position": 1,
        "thickness": 2
      }
    ],
    "do_objectID": "EB91542D-E6DB-43D6-A221-A969B08A26B0",
    "endMarkerType": 0,
    "fills": [
      {
        "_class": "fill",
        "color": {
          "_class": "color",
          "alpha": 1,
          "blue": 1,
          "green": 1,
          "red": 1
        },
        "fillType": 0,
        "isEnabled": false,
        "noiseIndex": 0,
        "noiseIntensity": 0,
        "patternFillType": 0,
        "patternTileScale": 1
      }
    ],
    "miterLimit": 10,
    "sharedObjectID": "F2A4BD62-EA39-4E54-8C20-90257328352B",
    "startMarkerType": 0,
    "windingRule": 1
  },
  "windingRule": 1
}