{
  "_class": "group",
  "booleanOperation": 0,
  "do_objectID": "4D591D0B-099C-4577-9982-CFA076A93E28",
  "exportOptions": {
    "_class": "exportOptions",
    "do_objectID": "29C3B978-E6DF-4ECE-B169-6481EAA93CD1",
    "exportFormats": [
    ],
    "includedLayerIds": [
    ],
    "layerOptions": 0,
    "shouldTrim": false
  },
  "frame": {
    "_class": "rect",
    "constrainProportions": false,
    "do_objectID": "8AE64757-4E8F-40C8-ABC2-B9A926852AF2",
    "height": 175,
    "width": 260,
    "x": 382,
    "y": 385
  },
  "hasClickThrough": false,
  "isFixedToViewport": false,
  "isFlippedHorizontal": false,
  "isFlippedVertical": false,
  "isLocked": false,
  "isVisible": true,
  "layerListExpandedType": 0,
  "layers": [
    {
      "class": "shapeGroup",
      "id": "8EE816D8-B760-4037-B4EB-CCF3ACEB4CC4"
    },
    {
      "class": "shapeGroup",
      "id": "38E6B8A3-FCA7-4078-B075-DA032221EE97"
    },
    {
      "class": "shapeGroup",
      "id": "8F6F4F65-62FE-4420-A63B-B7F459DDFC04"
    }
  ],
  "name": "image",
  "nameIsFixed": true,
  "resizingConstraint": 45,
  "resizingType": 0,
  "rotation": 0,
  "shouldBreakMaskChain": false,
  "style": {
    "_class": "style",
    "do_objectID": "4A2F87DE-4C9F-46D9-824B-439E275C4DB9",
    "endMarkerType": 0,
    "miterLimit": 10,
    "startMarkerType": 0,
    "windingRule": 1
  },
  "userInfo": {
    "com.animaapp.stc-sketch-plugin": {
      "kModelPropertiesKey": {
      }
    }
  }
}