{
  "_class": "shapeGroup",
  "booleanOperation": 0,
  "clippingMaskMode": 0,
  "do_objectID": "5945C40E-9ED5-412D-9600-A5FA188B5C38",
  "exportOptions": {
    "_class": "exportOptions",
    "do_objectID": "CCA143C8-F6F9-462D-BE69-31D0E6D4DD6C",
    "exportFormats": [
    ],
    "includedLayerIds": [
    ],
    "layerOptions": 0,
    "shouldTrim": false
  },
  "frame": {
    "_class": "rect",
    "constrainProportions": false,
    "do_objectID": "06C9336E-299B-42D4-9D2B-6B145F520073",
    "height": 531,
    "width": 793,
    "x": 1026,
    "y": 1601
  },
  "hasClickThrough": false,
  "hasClippingMask": false,
  "isFixedToViewport": false,
  "isFlippedHorizontal": false,
  "isFlippedVertical": false,
  "isLocked": false,
  "isVisible": true,
  "layerListExpandedType": 0,
  "layers": [
    {
      "class": "rectangle",
      "id": "2AB15454-EEE0-4F27-A92D-EC0F93DBC745"
    },
    {
      "class": "rectangle",
      "id": "D2DFBBE2-2527-464B-86E4-D9509CEBF8B4"
    }
  ],
  "name": "Landing Pages Box with Content",
  "nameIsFixed": true,
  "originalObjectID": "FD56ED63-6E53-4002-8BE5-B1BCA594405E",
  "resizingConstraint": 63,
  "resizingType": 0,
  "rotation": 0,
  "shouldBreakMaskChain": false,
  "style": {
    "_class": "style",
    "borders": [
      {
        "_class": "border",
        "color": {
          "_class": "color",
          "alpha": 1,
          "blue": 0.6079225540161133,
          "green": 0.6078033447265625,
          "red": 0.6078922152519226
        },
        "fillType": 0,
        "isEnabled": true,
        "position": 2,
        "thickness": 2
      }
    ],
    "do_objectID": "69DF20BA-D224-48DE-9DC2-C503E20A1165",
    "endMarkerType": 0,
    "fills": [
      {
        "_class": "fill",
        "color": {
          "_class": "color",
          "alpha": 1,
          "blue": 1,
          "green": 1,
          "red": 1
        },
        "fillType": 0,
        "isEnabled": true,
        "noiseIndex": 0,
        "noiseIntensity": 0,
        "patternFillType": 0,
        "patternTileScale": 1
      }
    ],
    "innerShadows": [
      {
        "_class": "innerShadow",
        "blurRadius": 0,
        "color": {
          "_class": "color",
          "alpha": 1,
          "blue": 0.9137254901960784,
          "green": 0.9137254901960784,
          "red": 0.9137254901960784
        },
        "contextSettings": {
          "_class": "graphicsContextSettings",
          "blendMode": 0,
          "opacity": 1
        },
        "isEnabled": false,
        "offsetX": 0,
        "offsetY": -1,
        "spread": 1
      }
    ],
    "miterLimit": 10,
    "shadows": [
      {
        "_class": "shadow",
        "blurRadius": 4,
        "color": {
          "_class": "color",
          "alpha": 0.5524513134057971,
          "blue": 0.9517166241496599,
          "green": 0.9517166241496599,
          "red": 0.9517166241496599
        },
        "contextSettings": {
          "_class": "graphicsContextSettings",
          "blendMode": 0,
          "opacity": 1
        },
        "isEnabled": true,
        "offsetX": 10,
        "offsetY": 12,
        "spread": 14
      }
    ],
    "sharedObjectID": "BECB60CC-B27B-4C6B-AFD2-B8E7A03E788F",
    "startMarkerType": 0,
    "windingRule": 1
  },
  "userInfo": {
    "com.animaapp.stc-sketch-plugin": {
      "kModelPropertiesKey": {
      }
    }
  },
  "windingRule": 1
}