{
  "_class": "group",
  "booleanOperation": 0,
  "do_objectID": "2B9A2C82-D348-48D2-ABD5-1B58B6833F05",
  "exportOptions": {
    "_class": "exportOptions",
    "do_objectID": "7737A65D-B626-4518-A6CC-45C4138E1D3B",
    "exportFormats": [
    ],
    "includedLayerIds": [
    ],
    "layerOptions": 0,
    "shouldTrim": false
  },
  "frame": {
    "_class": "rect",
    "constrainProportions": false,
    "do_objectID": "B2FCDFBD-AD27-42E5-82A6-F710C94DEBC9",
    "height": 85,
    "width": 125,
    "x": 186,
    "y": 1041
  },
  "hasClickThrough": false,
  "isFixedToViewport": false,
  "isFlippedHorizontal": false,
  "isFlippedVertical": false,
  "isLocked": false,
  "isVisible": true,
  "layerListExpandedType": 0,
  "layers": [
    {
      "class": "shapeGroup",
      "id": "C37202C4-1445-40AE-8A3E-CEE81FEC26B1"
    },
    {
      "class": "shapeGroup",
      "id": "7DE5976B-E4F0-47C7-9447-B18C721EE223"
    },
    {
      "class": "shapeGroup",
      "id": "4BC928A8-D9C6-462F-B657-6E92E4D8F209"
    }
  ],
  "name": "image",
  "nameIsFixed": true,
  "resizingConstraint": 45,
  "resizingType": 0,
  "rotation": 0,
  "shouldBreakMaskChain": false,
  "style": {
    "_class": "style",
    "do_objectID": "87740440-3110-4212-AD45-5190BF12FD3C",
    "endMarkerType": 0,
    "miterLimit": 10,
    "startMarkerType": 0,
    "windingRule": 1
  },
  "userInfo": {
    "com.animaapp.stc-sketch-plugin": {
      "kModelPropertiesKey": {
      }
    }
  }
}