{
  "_class": "group",
  "booleanOperation": -1,
  "do_objectID": "0F174995-2AB9-4279-8012-C7D8AAA0B655",
  "exportOptions": {
    "_class": "exportOptions",
    "do_objectID": "07A87B89-EB64-482A-B969-E9B54EAFBFED",
    "exportFormats": [
    ],
    "includedLayerIds": [
    ],
    "layerOptions": 0,
    "shouldTrim": false
  },
  "frame": {
    "_class": "rect",
    "constrainProportions": false,
    "do_objectID": "627897C0-90AC-45ED-8C91-1207FCDE0110",
    "height": 56,
    "width": 57,
    "x": 0,
    "y": 0
  },
  "hasClickThrough": false,
  "isFixedToViewport": false,
  "isFlippedHorizontal": false,
  "isFlippedVertical": false,
  "isLocked": false,
  "isVisible": true,
  "layerListExpandedType": 0,
  "layers": [
    {
      "class": "shapeGroup",
      "id": "F027D747-3ABD-44CD-B802-93394FF92B36"
    },
    {
      "class": "shapeGroup",
      "id": "1C33EC85-0FE0-4571-98D8-B7665E6D80CF"
    }
  ],
  "name": "LOGO",
  "nameIsFixed": true,
  "resizingConstraint": 63,
  "resizingType": 0,
  "rotation": 0,
  "shouldBreakMaskChain": false,
  "style": {
    "_class": "style",
    "do_objectID": "DF44E259-105F-489C-8EF5-1E2868A11F16",
    "endMarkerType": 0,
    "miterLimit": 10,
    "startMarkerType": 0,
    "windingRule": 1
  },
  "userInfo": {
    "com.animaapp.stc-sketch-plugin": {
      "kModelPropertiesKey": {
      }
    }
  }
}