{
  "_class": "shapeGroup",
  "booleanOperation": -1,
  "clippingMaskMode": 0,
  "do_objectID": "EAFC1933-60C5-4D10-A0F3-0F623C0E41D0",
  "exportOptions": {
    "_class": "exportOptions",
    "do_objectID": "57065D09-A9A5-4430-803A-49874E7229E0",
    "exportFormats": [
    ],
    "includedLayerIds": [
    ],
    "layerOptions": 0,
    "shouldTrim": false
  },
  "frame": {
    "_class": "rect",
    "constrainProportions": true,
    "do_objectID": "7658ECB0-D612-49E5-B400-1703B8EF373C",
    "height": 948,
    "width": 948,
    "x": 972,
    "y": 3579
  },
  "hasClickThrough": false,
  "hasClippingMask": false,
  "isFixedToViewport": false,
  "isFlippedHorizontal": false,
  "isFlippedVertical": false,
  "isLocked": false,
  "isVisible": true,
  "layerListExpandedType": 1,
  "layers": [
    {
      "class": "rectangle",
      "id": "D6216F32-0A15-4825-AE63-0E7F566ADB6D"
    }
  ],
  "name": "Rectangle 3 Copy 3",
  "nameIsFixed": false,
  "resizingConstraint": 63,
  "resizingType": 0,
  "rotation": 0,
  "shouldBreakMaskChain": false,
  "style": {
    "_class": "style",
    "borders": [
      {
        "_class": "border",
        "color": {
          "_class": "color",
          "alpha": 1,
          "blue": 0.592,
          "green": 0.592,
          "red": 0.592
        },
        "fillType": 0,
        "isEnabled": false,
        "position": 1,
        "thickness": 1
      }
    ],
    "do_objectID": "A9D8DC55-DA2A-4779-BCF0-377AE93D7D82",
    "endMarkerType": 0,
    "fills": [
      {
        "_class": "fill",
        "color": {
          "_class": "color",
          "alpha": 1,
          "blue": 0.9450980392156862,
          "green": 0.9450980392156862,
          "red": 0.9450980392156862
        },
        "fillType": 0,
        "isEnabled": true,
        "noiseIndex": 0,
        "noiseIntensity": 0,
        "patternFillType": 1,
        "patternTileScale": 1
      }
    ],
    "miterLimit": 10,
    "startMarkerType": 0,
    "windingRule": 1
  },
  "userInfo": {
    "com.animaapp.stc-sketch-plugin": {
      "kModelPropertiesKey": {
        "constraints": {
          "aspectRatio": {
            "constant": 948,
            "enabled": 1,
            "modelID": "constraint_5ff88d67-ace3-49db-aec6-92b728a94f98",
            "model_class": "ADModelConstraint",
            "model_version": 0.1,
            "multiplier": 948
          },
          "automatic": 1,
          "modelID": "viewConstraints_26e5158c-2fc3-4290-8f4a-3e21994c8eb5",
          "model_class": "ADModelViewConstraints",
          "model_version": 0.1,
          "scaleFactor": 1
        }
      }
    }
  },
  "windingRule": 1
}